mcd_usb_hub_ctrl/__init__.py
mcd_usb_hub_ctrl/mcd_usb_hub_ctrl.py
mcd_usb_hub_ctrl-0.2.0.dist-info/METADATA
mcd_usb_hub_ctrl-0.2.0.dist-info/WHEEL
mcd_usb_hub_ctrl-0.2.0.dist-info/licenses/LICENSE
mcd_usb_hub_ctrl-0.2.0.dist-info/RECORD
