Metadata-Version: 2.4
Name: mcd_usb_hub_ctrl
Version: 0.2.0
Summary: A lightwight python control module for MCD USB Hubs
Project-URL: Homepage, https://github.com/chriesibaum/mcd_usb_hub_ctrl
Author-email: Thomas Popp <thomas@chriesibaum.com>
License:                                  Apache License
License-File: LICENSE
Classifier: License :: OSI Approved :: Apache Software License
Classifier: Operating System :: OS Independent
Classifier: Programming Language :: Python :: 3
Requires-Python: >=3.12
Requires-Dist: pyserial
